CMakeLists.txt
MANIFEST.in
README.md
pyproject.toml
setup.cfg
setup.py
backend/atom_class.cpp
backend/atom_class.h
backend/atom_functions.cpp
backend/atom_functions.h
backend/coincidence_algorithm.cpp
backend/coincidence_algorithm.h
backend/helper_classes.cpp
backend/helper_classes.h
backend/interface_class.cpp
backend/interface_class.h
backend/logging_functions.cpp
backend/logging_functions.h
backend/math_functions.cpp
backend/math_functions.h
backend/pybindings.cpp
bin/hetbuilder
external/pybind11/.appveyor.yml
external/pybind11/.clang-format
external/pybind11/.clang-tidy
external/pybind11/.cmake-format.yaml
external/pybind11/.git
external/pybind11/.gitignore
external/pybind11/.pre-commit-config.yaml
external/pybind11/.readthedocs.yml
external/pybind11/CMakeLists.txt
external/pybind11/LICENSE
external/pybind11/MANIFEST.in
external/pybind11/README.rst
external/pybind11/pyproject.toml
external/pybind11/setup.cfg
external/pybind11/setup.py
external/pybind11/include/pybind11/attr.h
external/pybind11/include/pybind11/buffer_info.h
external/pybind11/include/pybind11/cast.h
external/pybind11/include/pybind11/chrono.h
external/pybind11/include/pybind11/common.h
external/pybind11/include/pybind11/complex.h
external/pybind11/include/pybind11/eigen.h
external/pybind11/include/pybind11/embed.h
external/pybind11/include/pybind11/eval.h
external/pybind11/include/pybind11/functional.h
external/pybind11/include/pybind11/gil.h
external/pybind11/include/pybind11/iostream.h
external/pybind11/include/pybind11/numpy.h
external/pybind11/include/pybind11/operators.h
external/pybind11/include/pybind11/options.h
external/pybind11/include/pybind11/pybind11.h
external/pybind11/include/pybind11/pytypes.h
external/pybind11/include/pybind11/stl.h
external/pybind11/include/pybind11/stl_bind.h
external/pybind11/include/pybind11/detail/class.h
external/pybind11/include/pybind11/detail/common.h
external/pybind11/include/pybind11/detail/descr.h
external/pybind11/include/pybind11/detail/init.h
hetbuilder.egg-info/PKG-INFO
hetbuilder.egg-info/SOURCES.txt
hetbuilder.egg-info/dependency_links.txt
hetbuilder.egg-info/requires.txt
hetbuilder.egg-info/top_level.txt
hetbuilder.egg-info/zip-safe