Metadata-Version: 2.1
Name: hetbuilder
Version: 0.6.75
Summary: A tool to build heterostructure interfaces based on coincidence lattice theory.
Home-page: https://github.com/romankempt/hetbuilder.git
Author: Roman Kempt
Author-email: roman.kempt@tu-dresden.de
License: MIT
Download-URL: https://github.com/romankempt/hetbuilder.git
Platform: UNKNOWN
Classifier: Operating System :: OS Independent
Classifier: Programming Language :: Python :: 3.9
Classifier: Programming Language :: C++
Classifier: Topic :: Scientific/Engineering :: Chemistry
Classifier: Topic :: Scientific/Engineering :: Physics
